{
  "success": true,
  "generated_at": "2026-02-23T06:00:57.253727+01:00",
  "location": {
    "lat": "43:36:39.6",
    "lon": "3:52:36.1"
  },
  "traditional": [
    {
      "date_iso": "2026-02-23",
      "date_formatted": "Lundi 23/02/2026",
      "saints": [
        "St-Lazare",
        "St-Polycarpe de Smyrne"
      ],
      "phase_percentage": 38.1,
      "cycle_trajectoire": "Lune Montante",
      "cycle_illumination": "Lune Croissante",
      "sunrise": "07:30",
      "sunset": "18:25",
      "daylight_duration": "10:54:51 (+2min 53s)",
      "moon_position_start": 43.42,
      "moon_position_end": 57.58,
      "nodes_info": [],
      "periods": [
        {
          "start_time": "00:00",
          "end_time": "00:00",
          "constellation": "Taureau",
          "recommendation": "Actions favorables aux légumes racines.",
          "seve_info": "Sève montante : idéal pour semer, greffer et récolter les fruits.",
          "blocked": false
        }
      ]
    },
    {
      "date_iso": "2026-02-24",
      "date_formatted": "Mardi 24/02/2026",
      "saints": [
        "St-Modeste",
        "Ste-Primitive"
      ],
      "phase_percentage": 49.4,
      "cycle_trajectoire": "Lune Montante",
      "cycle_illumination": "Lune Croissante",
      "sunrise": "07:29",
      "sunset": "18:26",
      "daylight_duration": "10:57:45 (+2min 54s)",
      "moon_position_start": 57.58,
      "moon_position_end": 71.78,
      "nodes_info": [],
      "periods": [
        {
          "start_time": "00:00",
          "end_time": "04:06",
          "constellation": "Taureau",
          "recommendation": "Actions favorables aux légumes racines.",
          "seve_info": "Sève montante : idéal pour semer, greffer et récolter les fruits.",
          "blocked": false
        },
        {
          "start_time": "04:06",
          "end_time": "00:00",
          "constellation": "Gémeaux",
          "recommendation": "Actions favorables aux fleurs et légumes fleurs.",
          "seve_info": "Sève montante : idéal pour semer, greffer et récolter les fruits.",
          "blocked": false
        }
      ]
    },
    {
      "date_iso": "2026-02-25",
      "date_formatted": "Mercredi 25/02/2026",
      "saints": [
        "St-Césaire de Nazianze",
        "St-Tarasius",
        "Ste-Walburge"
      ],
      "phase_percentage": 60.8,
      "cycle_trajectoire": "Lune Montante",
      "cycle_illumination": "Lune Croissante",
      "sunrise": "07:27",
      "sunset": "18:28",
      "daylight_duration": "11:00:40 (+2min 54s)",
      "moon_position_start": 71.78,
      "moon_position_end": 85.98,
      "nodes_info": [],
      "periods": [
        {
          "start_time": "00:00",
          "end_time": "00:00",
          "constellation": "Gémeaux",
          "recommendation": "Actions favorables aux fleurs et légumes fleurs.",
          "seve_info": "Sève montante : idéal pour semer, greffer et récolter les fruits.",
          "blocked": false
        }
      ]
    },
    {
      "date_iso": "2026-02-26",
      "date_formatted": "Jeudi 26/02/2026",
      "saints": [
        "St-Alexandre",
        "St-Nestor"
      ],
      "phase_percentage": 71.6,
      "cycle_trajectoire": "Lune Descendante",
      "cycle_illumination": "Lune Croissante",
      "sunrise": "07:25",
      "sunset": "18:29",
      "daylight_duration": "11:03:35 (+2min 55s)",
      "moon_position_start": 85.98,
      "moon_position_end": 100.14,
      "nodes_info": [],
      "periods": [
        {
          "start_time": "00:00",
          "end_time": "06:48",
          "constellation": "Gémeaux",
          "recommendation": "Actions favorables aux fleurs et légumes fleurs.",
          "seve_info": "Sève descendante : idéal pour planter, repiquer, tailler et récolter les légumes racines.",
          "blocked": false
        },
        {
          "start_time": "06:48",
          "end_time": "00:00",
          "constellation": "Cancer",
          "recommendation": "Actions favorables aux légumes feuilles.",
          "seve_info": "Sève descendante : idéal pour planter, repiquer, tailler et récolter les légumes racines.",
          "blocked": false
        }
      ]
    },
    {
      "date_iso": "2026-02-27",
      "date_formatted": "Vendredi 27/02/2026",
      "saints": [
        "St-Gabriel de l'Addolorata",
        "Ste-Honorine"
      ],
      "phase_percentage": 81.3,
      "cycle_trajectoire": "Lune Descendante",
      "cycle_illumination": "Lune Croissante",
      "sunrise": "07:24",
      "sunset": "18:30",
      "daylight_duration": "11:06:31 (+2min 55s)",
      "moon_position_start": 100.14,
      "moon_position_end": 114.22,
      "nodes_info": [],
      "periods": [
        {
          "start_time": "00:00",
          "end_time": "00:00",
          "constellation": "Cancer",
          "recommendation": "Actions favorables aux légumes feuilles.",
          "seve_info": "Sève descendante : idéal pour planter, repiquer, tailler et récolter les légumes racines.",
          "blocked": false
        }
      ]
    },
    {
      "date_iso": "2026-02-28",
      "date_formatted": "Samedi 28/02/2026",
      "saints": [
        "St-Hilaire, pape",
        "St-Romain de Condat",
        "St-Théophile d'Adana"
      ],
      "phase_percentage": 89.2,
      "cycle_trajectoire": "Lune Descendante",
      "cycle_illumination": "Lune Croissante",
      "sunrise": "07:22",
      "sunset": "18:32",
      "daylight_duration": "11:09:27 (+2min 56s)",
      "moon_position_start": 114.22,
      "moon_position_end": 128.17,
      "nodes_info": [],
      "periods": [
        {
          "start_time": "00:00",
          "end_time": "09:54",
          "constellation": "Cancer",
          "recommendation": "Actions favorables aux légumes feuilles.",
          "seve_info": "Sève descendante : idéal pour planter, repiquer, tailler et récolter les légumes racines.",
          "blocked": false
        },
        {
          "start_time": "09:54",
          "end_time": "00:00",
          "constellation": "Lion",
          "recommendation": "Actions favorables aux légumes fruits, graines et arbres fruitiers.",
          "seve_info": "Sève descendante : idéal pour planter, repiquer, tailler et récolter les légumes racines.",
          "blocked": false
        }
      ]
    },
    {
      "date_iso": "2026-03-01",
      "date_formatted": "Dimanche 01/03/2026",
      "saints": [
        "St-Albin d'Anvers",
        "St-Charles le bon",
        "St-Guénolé",
        "Ste-Cunégonde"
      ],
      "phase_percentage": 95.2,
      "cycle_trajectoire": "Lune Descendante",
      "cycle_illumination": "Lune Croissante",
      "sunrise": "07:20",
      "sunset": "18:33",
      "daylight_duration": "11:12:24 (+2min 56s)",
      "moon_position_start": 128.17,
      "moon_position_end": 141.95,
      "nodes_info": [],
      "periods": [
        {
          "start_time": "00:00",
          "end_time": "00:00",
          "constellation": "Lion",
          "recommendation": "Actions favorables aux légumes fruits, graines et arbres fruitiers.",
          "seve_info": "Sève descendante : idéal pour planter, repiquer, tailler et récolter les légumes racines.",
          "blocked": false
        }
      ]
    }
  ],
  "constellation": [
    {
      "date_iso": "2026-02-23",
      "date_formatted": "Lundi 23/02/2026",
      "saints": [
        "St-Lazare",
        "St-Polycarpe de Smyrne"
      ],
      "phase_percentage": 38.1,
      "cycle_trajectoire": "Lune Montante",
      "cycle_illumination": "Lune Croissante",
      "sunrise": "07:30",
      "sunset": "18:25",
      "daylight_duration": "10:54:51 (+2min 53s)",
      "moon_position_start": 43.42,
      "moon_position_end": 57.58,
      "nodes_info": [],
      "periods": [
        {
          "start_time": "00:00",
          "end_time": "17:56",
          "constellation": "Bélier",
          "recommendation": "Actions favorables aux légumes fruits, graines et arbres fruitiers.",
          "seve_info": "Sève montante : idéal pour semer, greffer et récolter les fruits.",
          "blocked": false
        },
        {
          "start_time": "17:56",
          "end_time": "00:00",
          "constellation": "Taureau",
          "recommendation": "Actions favorables aux légumes racines.",
          "seve_info": "Sève montante : idéal pour semer, greffer et récolter les fruits.",
          "blocked": false
        }
      ]
    },
    {
      "date_iso": "2026-02-24",
      "date_formatted": "Mardi 24/02/2026",
      "saints": [
        "St-Modeste",
        "Ste-Primitive"
      ],
      "phase_percentage": 49.4,
      "cycle_trajectoire": "Lune Montante",
      "cycle_illumination": "Lune Croissante",
      "sunrise": "07:29",
      "sunset": "18:26",
      "daylight_duration": "10:57:45 (+2min 54s)",
      "moon_position_start": 57.58,
      "moon_position_end": 71.78,
      "nodes_info": [],
      "periods": [
        {
          "start_time": "00:00",
          "end_time": "00:00",
          "constellation": "Taureau",
          "recommendation": "Actions favorables aux légumes racines.",
          "seve_info": "Sève montante : idéal pour semer, greffer et récolter les fruits.",
          "blocked": false
        }
      ]
    },
    {
      "date_iso": "2026-02-25",
      "date_formatted": "Mercredi 25/02/2026",
      "saints": [
        "St-Césaire de Nazianze",
        "St-Tarasius",
        "Ste-Walburge"
      ],
      "phase_percentage": 60.8,
      "cycle_trajectoire": "Lune Montante",
      "cycle_illumination": "Lune Croissante",
      "sunrise": "07:27",
      "sunset": "18:28",
      "daylight_duration": "11:00:40 (+2min 54s)",
      "moon_position_start": 71.78,
      "moon_position_end": 85.98,
      "nodes_info": [],
      "periods": [
        {
          "start_time": "00:00",
          "end_time": "00:00",
          "constellation": "Taureau",
          "recommendation": "Actions favorables aux légumes racines.",
          "seve_info": "Sève montante : idéal pour semer, greffer et récolter les fruits.",
          "blocked": false
        }
      ]
    },
    {
      "date_iso": "2026-02-26",
      "date_formatted": "Jeudi 26/02/2026",
      "saints": [
        "St-Alexandre",
        "St-Nestor"
      ],
      "phase_percentage": 71.6,
      "cycle_trajectoire": "Lune Descendante",
      "cycle_illumination": "Lune Croissante",
      "sunrise": "07:25",
      "sunset": "18:29",
      "daylight_duration": "11:03:35 (+2min 55s)",
      "moon_position_start": 85.98,
      "moon_position_end": 100.14,
      "nodes_info": [],
      "periods": [
        {
          "start_time": "00:00",
          "end_time": "06:48",
          "constellation": "Taureau",
          "recommendation": "Actions favorables aux légumes racines.",
          "seve_info": "Sève descendante : idéal pour planter, repiquer, tailler et récolter les légumes racines.",
          "blocked": false
        },
        {
          "start_time": "06:48",
          "end_time": "00:00",
          "constellation": "Gémeaux",
          "recommendation": "Actions favorables aux fleurs et légumes fleurs.",
          "seve_info": "Sève descendante : idéal pour planter, repiquer, tailler et récolter les légumes racines.",
          "blocked": false
        }
      ]
    },
    {
      "date_iso": "2026-02-27",
      "date_formatted": "Vendredi 27/02/2026",
      "saints": [
        "St-Gabriel de l'Addolorata",
        "Ste-Honorine"
      ],
      "phase_percentage": 81.3,
      "cycle_trajectoire": "Lune Descendante",
      "cycle_illumination": "Lune Croissante",
      "sunrise": "07:24",
      "sunset": "18:30",
      "daylight_duration": "11:06:31 (+2min 55s)",
      "moon_position_start": 100.14,
      "moon_position_end": 114.22,
      "nodes_info": [],
      "periods": [
        {
          "start_time": "00:00",
          "end_time": "00:00",
          "constellation": "Gémeaux",
          "recommendation": "Actions favorables aux fleurs et légumes fleurs.",
          "seve_info": "Sève descendante : idéal pour planter, repiquer, tailler et récolter les légumes racines.",
          "blocked": false
        }
      ]
    },
    {
      "date_iso": "2026-02-28",
      "date_formatted": "Samedi 28/02/2026",
      "saints": [
        "St-Hilaire, pape",
        "St-Romain de Condat",
        "St-Théophile d'Adana"
      ],
      "phase_percentage": 89.2,
      "cycle_trajectoire": "Lune Descendante",
      "cycle_illumination": "Lune Croissante",
      "sunrise": "07:22",
      "sunset": "18:32",
      "daylight_duration": "11:09:27 (+2min 56s)",
      "moon_position_start": 114.22,
      "moon_position_end": 128.17,
      "nodes_info": [],
      "periods": [
        {
          "start_time": "00:00",
          "end_time": "09:54",
          "constellation": "Gémeaux",
          "recommendation": "Actions favorables aux fleurs et légumes fleurs.",
          "seve_info": "Sève descendante : idéal pour planter, repiquer, tailler et récolter les légumes racines.",
          "blocked": false
        },
        {
          "start_time": "09:54",
          "end_time": "00:00",
          "constellation": "Cancer",
          "recommendation": "Actions favorables aux légumes feuilles.",
          "seve_info": "Sève descendante : idéal pour planter, repiquer, tailler et récolter les légumes racines.",
          "blocked": false
        }
      ]
    },
    {
      "date_iso": "2026-03-01",
      "date_formatted": "Dimanche 01/03/2026",
      "saints": [
        "St-Albin d'Anvers",
        "St-Charles le bon",
        "St-Guénolé",
        "Ste-Cunégonde"
      ],
      "phase_percentage": 95.2,
      "cycle_trajectoire": "Lune Descendante",
      "cycle_illumination": "Lune Croissante",
      "sunrise": "07:20",
      "sunset": "18:33",
      "daylight_duration": "11:12:24 (+2min 56s)",
      "moon_position_start": 128.17,
      "moon_position_end": 141.95,
      "nodes_info": [],
      "periods": [
        {
          "start_time": "00:00",
          "end_time": "17:05",
          "constellation": "Cancer",
          "recommendation": "Actions favorables aux légumes feuilles.",
          "seve_info": "Sève descendante : idéal pour planter, repiquer, tailler et récolter les légumes racines.",
          "blocked": false
        },
        {
          "start_time": "17:05",
          "end_time": "00:00",
          "constellation": "Lion",
          "recommendation": "Actions favorables aux légumes fruits, graines et arbres fruitiers.",
          "seve_info": "Sève descendante : idéal pour planter, repiquer, tailler et récolter les légumes racines.",
          "blocked": false
        }
      ]
    }
  ]
}