{
  "success": true,
  "generated_at": "2025-11-17T06:01:15.090974+01:00",
  "location": {
    "lat": "43:42:36.7",
    "lon": "7:15:43.2"
  },
  "traditional": [
    {
      "date_iso": "2025-11-17",
      "date_formatted": "Lundi 17/11/2025",
      "saints": [
        "St-Aignan",
        "Ste-Elisabeth de Hongrie",
        "St-Grégoire le Thaumaturge"
      ],
      "phase_percentage": 7.1,
      "cycle_trajectoire": "Lune Descendante",
      "cycle_illumination": "Lune Décroissante",
      "sunrise": "07:27",
      "sunset": "17:03",
      "daylight_duration": "09:36:23 (-2min 10s)",
      "moon_position_start": 198.34,
      "moon_position_end": 210.26,
      "nodes_info": [],
      "periods": [
        {
          "start_time": "00:00",
          "end_time": "23:28",
          "constellation": "Balance",
          "recommendation": "Actions favorables aux fleurs et légumes fleurs.",
          "seve_info": "Sève descendante : idéal pour planter, repiquer, tailler et récolter les légumes racines.",
          "blocked": false
        },
        {
          "start_time": "23:28",
          "end_time": "00:00",
          "constellation": "Scorpion",
          "recommendation": "Actions favorables aux légumes feuilles.",
          "seve_info": "Sève descendante : idéal pour planter, repiquer, tailler et récolter les légumes racines.",
          "blocked": false
        }
      ]
    },
    {
      "date_iso": "2025-11-18",
      "date_formatted": "Mardi 18/11/2025",
      "saints": [
        "St-Hésyque d'Antioche",
        "St-Mummole",
        "St-Pierre, apôtre",
        "St-Tanguy"
      ],
      "phase_percentage": 3.1,
      "cycle_trajectoire": "Lune Descendante",
      "cycle_illumination": "Lune Décroissante",
      "sunrise": "07:28",
      "sunset": "17:03",
      "daylight_duration": "09:34:15 (-2min 7s)",
      "moon_position_start": 210.26,
      "moon_position_end": 222.13,
      "nodes_info": [],
      "periods": [
        {
          "start_time": "00:00",
          "end_time": "00:00",
          "constellation": "Scorpion",
          "recommendation": "Actions favorables aux légumes feuilles.",
          "seve_info": "Sève descendante : idéal pour planter, repiquer, tailler et récolter les légumes racines.",
          "blocked": false
        }
      ]
    },
    {
      "date_iso": "2025-11-19",
      "date_formatted": "Mercredi 19/11/2025",
      "saints": [
        "Ste-Ermenburge",
        "St-Exupère"
      ],
      "phase_percentage": 0.8,
      "cycle_trajectoire": "Lune Descendante",
      "cycle_illumination": "Lune Décroissante",
      "sunrise": "07:30",
      "sunset": "17:02",
      "daylight_duration": "09:32:10 (-2min 5s)",
      "moon_position_start": 222.13,
      "moon_position_end": 233.99,
      "nodes_info": [],
      "periods": [
        {
          "start_time": "00:00",
          "end_time": "00:00",
          "constellation": "Scorpion",
          "recommendation": "Actions favorables aux légumes feuilles.",
          "seve_info": "Sève descendante : idéal pour planter, repiquer, tailler et récolter les légumes racines.",
          "blocked": false
        }
      ]
    },
    {
      "date_iso": "2025-11-20",
      "date_formatted": "Jeudi 20/11/2025",
      "saints": [
        "St-Edmond",
        "St-Félix de Valois",
        "St-Octave"
      ],
      "phase_percentage": 0.2,
      "cycle_trajectoire": "Lune Descendante",
      "cycle_illumination": "Lune Croissante",
      "sunrise": "07:31",
      "sunset": "17:01",
      "daylight_duration": "09:30:07 (-2min 2s)",
      "moon_position_start": 233.99,
      "moon_position_end": 245.85,
      "nodes_info": [],
      "periods": [
        {
          "start_time": "00:00",
          "end_time": "12:09",
          "constellation": "Scorpion",
          "recommendation": "Actions favorables aux légumes feuilles.",
          "seve_info": "Sève descendante : idéal pour planter, repiquer, tailler et récolter les légumes racines.",
          "blocked": false
        },
        {
          "start_time": "12:09",
          "end_time": "00:00",
          "constellation": "Sagittaire",
          "recommendation": "Actions favorables aux légumes fruits, graines et arbres fruitiers.",
          "seve_info": "Sève descendante : idéal pour planter, repiquer, tailler et récolter les légumes racines.",
          "blocked": false
        }
      ]
    },
    {
      "date_iso": "2025-11-21",
      "date_formatted": "Vendredi 21/11/2025",
      "saints": [
        "Ste-Amalberge",
        "Présence de Marie"
      ],
      "phase_percentage": 1.4,
      "cycle_trajectoire": "Lune Descendante",
      "cycle_illumination": "Lune Croissante",
      "sunrise": "07:32",
      "sunset": "17:00",
      "daylight_duration": "09:28:08 (-1min 59s)",
      "moon_position_start": 245.85,
      "moon_position_end": 257.75,
      "nodes_info": [],
      "periods": [
        {
          "start_time": "00:00",
          "end_time": "00:00",
          "constellation": "Sagittaire",
          "recommendation": "Actions favorables aux légumes fruits, graines et arbres fruitiers.",
          "seve_info": "Sève descendante : idéal pour planter, repiquer, tailler et récolter les légumes racines.",
          "blocked": false
        }
      ]
    },
    {
      "date_iso": "2025-11-22",
      "date_formatted": "Samedi 22/11/2025",
      "saints": [
        "Ste-Appia",
        "Ste-Cécile",
        "St-Philémon"
      ],
      "phase_percentage": 4.4,
      "cycle_trajectoire": "Lune Descendante",
      "cycle_illumination": "Lune Croissante",
      "sunrise": "07:33",
      "sunset": "17:00",
      "daylight_duration": "09:26:11 (-1min 57s)",
      "moon_position_start": 257.75,
      "moon_position_end": 269.7,
      "nodes_info": [],
      "periods": [
        {
          "start_time": "00:00",
          "end_time": "00:00",
          "constellation": "Sagittaire",
          "recommendation": "Actions favorables aux légumes fruits, graines et arbres fruitiers.",
          "seve_info": "Sève descendante : idéal pour planter, repiquer, tailler et récolter les légumes racines.",
          "blocked": false
        }
      ]
    },
    {
      "date_iso": "2025-11-23",
      "date_formatted": "Dimanche 23/11/2025",
      "saints": [
        "St-Clément 1er"
      ],
      "phase_percentage": 9.0,
      "cycle_trajectoire": "Lune Montante",
      "cycle_illumination": "Lune Croissante",
      "sunrise": "07:35",
      "sunset": "16:59",
      "daylight_duration": "09:24:17 (-1min 54s)",
      "moon_position_start": 269.7,
      "moon_position_end": 281.73,
      "nodes_info": [],
      "periods": [
        {
          "start_time": "00:00",
          "end_time": "00:36",
          "constellation": "Sagittaire",
          "recommendation": "Actions favorables aux légumes fruits, graines et arbres fruitiers.",
          "seve_info": "Sève montante : idéal pour semer, greffer et récolter les fruits.",
          "blocked": false
        },
        {
          "start_time": "00:36",
          "end_time": "00:00",
          "constellation": "Capricorne",
          "recommendation": "Actions favorables aux légumes racines.",
          "seve_info": "Sève montante : idéal pour semer, greffer et récolter les fruits.",
          "blocked": false
        }
      ]
    }
  ],
  "constellation": [
    {
      "date_iso": "2025-11-17",
      "date_formatted": "Lundi 17/11/2025",
      "saints": [
        "St-Aignan",
        "Ste-Elisabeth de Hongrie",
        "St-Grégoire le Thaumaturge"
      ],
      "phase_percentage": 7.1,
      "cycle_trajectoire": "Lune Descendante",
      "cycle_illumination": "Lune Décroissante",
      "sunrise": "07:27",
      "sunset": "17:03",
      "daylight_duration": "09:36:23 (-2min 10s)",
      "moon_position_start": 198.34,
      "moon_position_end": 210.26,
      "nodes_info": [],
      "periods": [
        {
          "start_time": "00:00",
          "end_time": "00:00",
          "constellation": "Vierge",
          "recommendation": "Actions favorables aux légumes racines.",
          "seve_info": "Sève descendante : idéal pour planter, repiquer, tailler et récolter les légumes racines.",
          "blocked": false
        }
      ]
    },
    {
      "date_iso": "2025-11-18",
      "date_formatted": "Mardi 18/11/2025",
      "saints": [
        "St-Hésyque d'Antioche",
        "St-Mummole",
        "St-Pierre, apôtre",
        "St-Tanguy"
      ],
      "phase_percentage": 3.1,
      "cycle_trajectoire": "Lune Descendante",
      "cycle_illumination": "Lune Décroissante",
      "sunrise": "07:28",
      "sunset": "17:03",
      "daylight_duration": "09:34:15 (-2min 7s)",
      "moon_position_start": 210.26,
      "moon_position_end": 222.13,
      "nodes_info": [],
      "periods": [
        {
          "start_time": "00:00",
          "end_time": "15:38",
          "constellation": "Vierge",
          "recommendation": "Actions favorables aux légumes racines.",
          "seve_info": "Sève descendante : idéal pour planter, repiquer, tailler et récolter les légumes racines.",
          "blocked": false
        },
        {
          "start_time": "15:38",
          "end_time": "00:00",
          "constellation": "Balance",
          "recommendation": "Actions favorables aux fleurs et légumes fleurs.",
          "seve_info": "Sève descendante : idéal pour planter, repiquer, tailler et récolter les légumes racines.",
          "blocked": false
        }
      ]
    },
    {
      "date_iso": "2025-11-19",
      "date_formatted": "Mercredi 19/11/2025",
      "saints": [
        "Ste-Ermenburge",
        "St-Exupère"
      ],
      "phase_percentage": 0.8,
      "cycle_trajectoire": "Lune Descendante",
      "cycle_illumination": "Lune Décroissante",
      "sunrise": "07:30",
      "sunset": "17:02",
      "daylight_duration": "09:32:10 (-2min 5s)",
      "moon_position_start": 222.13,
      "moon_position_end": 233.99,
      "nodes_info": [],
      "periods": [
        {
          "start_time": "00:00",
          "end_time": "00:00",
          "constellation": "Balance",
          "recommendation": "Actions favorables aux fleurs et légumes fleurs.",
          "seve_info": "Sève descendante : idéal pour planter, repiquer, tailler et récolter les légumes racines.",
          "blocked": false
        }
      ]
    },
    {
      "date_iso": "2025-11-20",
      "date_formatted": "Jeudi 20/11/2025",
      "saints": [
        "St-Edmond",
        "St-Félix de Valois",
        "St-Octave"
      ],
      "phase_percentage": 0.2,
      "cycle_trajectoire": "Lune Descendante",
      "cycle_illumination": "Lune Croissante",
      "sunrise": "07:31",
      "sunset": "17:01",
      "daylight_duration": "09:30:07 (-2min 2s)",
      "moon_position_start": 233.99,
      "moon_position_end": 245.85,
      "nodes_info": [],
      "periods": [
        {
          "start_time": "00:00",
          "end_time": "14:11",
          "constellation": "Balance",
          "recommendation": "Actions favorables aux fleurs et légumes fleurs.",
          "seve_info": "Sève descendante : idéal pour planter, repiquer, tailler et récolter les légumes racines.",
          "blocked": false
        },
        {
          "start_time": "14:11",
          "end_time": "00:00",
          "constellation": "Scorpion",
          "recommendation": "Actions favorables aux légumes feuilles.",
          "seve_info": "Sève descendante : idéal pour planter, repiquer, tailler et récolter les légumes racines.",
          "blocked": false
        }
      ]
    },
    {
      "date_iso": "2025-11-21",
      "date_formatted": "Vendredi 21/11/2025",
      "saints": [
        "Ste-Amalberge",
        "Présence de Marie"
      ],
      "phase_percentage": 1.4,
      "cycle_trajectoire": "Lune Descendante",
      "cycle_illumination": "Lune Croissante",
      "sunrise": "07:32",
      "sunset": "17:00",
      "daylight_duration": "09:28:08 (-1min 59s)",
      "moon_position_start": 245.85,
      "moon_position_end": 257.75,
      "nodes_info": [],
      "periods": [
        {
          "start_time": "00:00",
          "end_time": "04:20",
          "constellation": "Scorpion",
          "recommendation": "Actions favorables aux légumes feuilles.",
          "seve_info": "Sève descendante : idéal pour planter, repiquer, tailler et récolter les légumes racines.",
          "blocked": false
        },
        {
          "start_time": "04:20",
          "end_time": "00:00",
          "constellation": "Serpentaire",
          "recommendation": "Période de repos et guérison, pas de jardinage recommandé.",
          "seve_info": "",
          "blocked": false
        }
      ]
    },
    {
      "date_iso": "2025-11-22",
      "date_formatted": "Samedi 22/11/2025",
      "saints": [
        "Ste-Appia",
        "Ste-Cécile",
        "St-Philémon"
      ],
      "phase_percentage": 4.4,
      "cycle_trajectoire": "Lune Descendante",
      "cycle_illumination": "Lune Croissante",
      "sunrise": "07:33",
      "sunset": "17:00",
      "daylight_duration": "09:26:11 (-1min 57s)",
      "moon_position_start": 257.75,
      "moon_position_end": 269.7,
      "nodes_info": [],
      "periods": [
        {
          "start_time": "00:00",
          "end_time": "16:35",
          "constellation": "Serpentaire",
          "recommendation": "Période de repos et guérison, pas de jardinage recommandé.",
          "seve_info": "",
          "blocked": false
        },
        {
          "start_time": "16:35",
          "end_time": "00:00",
          "constellation": "Sagittaire",
          "recommendation": "Actions favorables aux légumes fruits, graines et arbres fruitiers.",
          "seve_info": "Sève descendante : idéal pour planter, repiquer, tailler et récolter les légumes racines.",
          "blocked": false
        }
      ]
    },
    {
      "date_iso": "2025-11-23",
      "date_formatted": "Dimanche 23/11/2025",
      "saints": [
        "St-Clément 1er"
      ],
      "phase_percentage": 9.0,
      "cycle_trajectoire": "Lune Montante",
      "cycle_illumination": "Lune Croissante",
      "sunrise": "07:35",
      "sunset": "16:59",
      "daylight_duration": "09:24:17 (-1min 54s)",
      "moon_position_start": 269.7,
      "moon_position_end": 281.73,
      "nodes_info": [],
      "periods": [
        {
          "start_time": "00:00",
          "end_time": "00:00",
          "constellation": "Sagittaire",
          "recommendation": "Actions favorables aux légumes fruits, graines et arbres fruitiers.",
          "seve_info": "Sève montante : idéal pour semer, greffer et récolter les fruits.",
          "blocked": false
        }
      ]
    }
  ]
}